crowdcores_node/__init__.py
crowdcores_node/crowdcores_node.py
crowdcores_node/manager.py
crowdcores_node/node.py
crowdcores_node-1.1.6.dist-info/LICENSE.txt
crowdcores_node-1.1.6.dist-info/METADATA
crowdcores_node-1.1.6.dist-info/WHEEL
crowdcores_node-1.1.6.dist-info/entry_points.txt
crowdcores_node-1.1.6.dist-info/top_level.txt
crowdcores_node-1.1.6.dist-info/RECORD
