Metadata-Version: 2.1
Name: crowdcores-node
Version: 1.1.6
License-File: LICENSE.txt
Requires-Dist: websockets
Requires-Dist: torch
Requires-Dist: transformers
Requires-Dist: psutil
